LICENSE
MANIFEST.in
README.md
requirements.txt
setup.py
htu21/__init__.py
htu21/htu21.py
htu21/rawi2c.py
htu21/retry.py
htu21df.egg-info/PKG-INFO
htu21df.egg-info/SOURCES.txt
htu21df.egg-info/dependency_links.txt
htu21df.egg-info/not-zip-safe
htu21df.egg-info/requires.txt
htu21df.egg-info/top_level.txt