Metadata-Version: 1.1
Name: htu21df
Version: 0.1.4
Summary: A simple program for controlling an htu21d-f sensor from a Raspberry Pi
Home-page: https://github.com/MSeal/htu21df_sensor
Author: Matthew Seal
Author-email: mseal007@gmail.com
License: MIT
Download-URL: https://github.com/MSeal/htu21df_sensor/tarball/v0.1.4
Keywords: sensors,raspberry_pi,adafruit,scripting
Platform: UNKNOWN
Classifier: Development Status :: 4 - Beta
Classifier: Topic :: Utilities
Classifier: License :: OSI Approved :: MIT License
Classifier: Natural Language :: English
Classifier: Programming Language :: Python
